{
	"info": {
		"_postman_id": "57161e54-1383-488b-80a7-a8afb98fd25b",
		"name": "Stones_API",
		"schema": "https://schema.getpostman.com/json/collection/v2.1.0/collection.json",
		"_exporter_id": "21469886"
	},
	"item": [
		{
			"name": "Get_All_Stones",
			"request": {
				"method": "GET",
				"header": []
			},
			"response": []
		},
		{
			"name": "Create_Stone",
			"request": {
				"method": "GET",
				"header": []
			},
			"response": []
		},
		{
			"name": "Get_Stone_By_id",
			"request": {
				"method": "GET",
				"header": []
			},
			"response": []
		},
		{
			"name": "Update_Stone",
			"request": {
				"method": "GET",
				"header": []
			},
			"response": []
		},
		{
			"name": "DELETE_Stone",
			"request": {
				"method": "GET",
				"header": []
			},
			"response": []
		}
	]
}